handtruck/__init__.py
handtruck/_async.py
handtruck/_xml.py
handtruck/client.py
handtruck/credentials.py
handtruck/py.typed
handtruck/version.py
handtruck-0.0.1.dist-info/METADATA
handtruck-0.0.1.dist-info/WHEEL
handtruck-0.0.1.dist-info/licenses/LICENSE
handtruck-0.0.1.dist-info/licenses/LICENSE.md
handtruck-0.0.1.dist-info/RECORD
