Metadata-Version: 2.4
Name: handtruck
Version: 0.0.1
Summary: Async S3 client using httpx & anyio
License: Apache Software License
License-File: LICENSE
License-File: LICENSE.md
Author: Vladimir Morugin
Author-email: vamorugin@gmail.com
Maintainer: Jamie Bliss
Maintainer-email: jamie@teahouse.cafe
Requires-Python: >=3.11,<4.0
Classifier: Development Status :: 4 - Beta
Classifier: Intended Audience :: Developers
Classifier: License :: OSI Approved :: Apache Software License
Classifier: License :: Other/Proprietary License
Classifier: Natural Language :: English
Classifier: Operating System :: MacOS
Classifier: Operating System :: Microsoft
Classifier: Operating System :: POSIX
Classifier: Programming Language :: Python :: 3
Classifier: Programming Language :: Python :: 3.11
Classifier: Programming Language :: Python :: 3.12
Classifier: Programming Language :: Python :: 3.13
Classifier: Programming Language :: Python :: 3.14
Classifier: Programming Language :: Python :: Implementation :: CPython
Classifier: Programming Language :: Python :: Implementation :: PyPy
Classifier: Topic :: Internet
Classifier: Topic :: Software Development
Classifier: Topic :: Software Development :: Libraries
Requires-Dist: anyio (>=3.7.1)
Requires-Dist: aws-request-signer (==1.2.0)
Requires-Dist: httpcore (>=1.0.8) ; python_version >= "3.14"
Requires-Dist: httpx (>=0.28.1)
Project-URL: Homepage, https://codeberg.org/teahouse/handtruck
Project-URL: Source, https://codeberg.org/teahouse/handtruck
